Metadata-Version: 2.1
Name: probability-distributions-functions
Version: 1.1
Summary: Gaussian and Binomial Probability distributions
Home-page: https://github.com/Moddy2024/Probability-Distribution-Functions
Author: Modassir Afzal
Author-email: modassir2024@gmail.com
License: UNKNOWN
Platform: UNKNOWN
